hashwise/__init__.py
hashwise/device_status.py
hashwise/exceptions.py
hashwise/hashwise.py
hashwise/cuda-libraries/cudalib-windows-64bit.dll
hashwise/device-info/device-info.dll
hashwise-0.0.4.dist-info/METADATA
hashwise-0.0.4.dist-info/WHEEL
hashwise-0.0.4.dist-info/top_level.txt
hashwise-0.0.4.dist-info/RECORD
