Metadata-Version: 2.1
Name: hashwise
Version: 0.0.4
Summary: A secure python library for GPU accelerated hashing.
Author: Anish Kanthamneni
Author-email: akneni@gmail.com
Requires-Dist: tqdm
Requires-Dist: pathlib
